office365/__init__.py
office365/base_item.py
office365/delta_collection.py
office365/delta_path.py
office365/entity.py
office365/entity_collection.py
office365/graph_client.py
office365/graph_request.py
office365/logger.py
office365/booking/__init__.py
office365/booking/appointment.py
office365/booking/currency.py
office365/booking/custom_question.py
office365/booking/service.py
office365/booking/work_hours.py
office365/booking/work_time_slot.py
office365/booking/business/__init__.py
office365/booking/business/business.py
office365/booking/business/collection.py
office365/booking/customers/__init__.py
office365/booking/customers/base.py
office365/booking/solutions/__init__.py
office365/booking/solutions/root.py
office365/booking/staff/__init__.py
office365/booking/staff/availability_item.py
office365/booking/staff/member_base.py
office365/booking/virtualevents/__init__.py
office365/booking/virtualevents/root.py
office365/communications/__init__.py
office365/communications/cloud_communications.py
office365/communications/result_info.py
office365/communications/callrecords/__init__.py
office365/communications/callrecords/call_record.py
office365/communications/callrecords/endpoint.py
office365/communications/callrecords/segment.py
office365/communications/callrecords/session.py
office365/communications/calls/__init__.py
office365/communications/calls/call.py
office365/communications/calls/collection.py
office365/communications/calls/incoming_context.py
office365/communications/calls/invitation_participant_info.py
office365/communications/calls/options.py
office365/communications/calls/participant.py
office365/communications/calls/participant_info.py
office365/communications/calls/route.py
office365/communications/meetings/__init__.py
office365/communications/meetings/info.py
office365/communications/meetings/join_meeting_id_info.py
office365/communications/onlinemeetings/__init__.py
office365/communications/onlinemeetings/collection.py
Office365_REST_Python_Client-2.5.12.dist-info/LICENSE
Office365_REST_Python_Client-2.5.12.dist-info/METADATA
Office365_REST_Python_Client-2.5.12.dist-info/WHEEL
Office365_REST_Python_Client-2.5.12.dist-info/top_level.txt
Office365_REST_Python_Client-2.5.12.dist-info/RECORD
