Metadata-Version: 2.1
Name: Office365-REST-Python-Client
Version: 2.5.12
Summary: Microsoft 365 & Microsoft Graph Library for Python
Home-page: https://github.com/vgrem/Office365-REST-Python-Client
Author: Vadim Gremyachev
Author-email: vvgrem@gmail.com
Maintainer: Konrad Gądek, Domenico Di Nicola
Maintainer-email: kgadek@gmail.com, dom.dinicola@gmail.com
License: MIT
Keywords: git
Classifier: Development Status :: 4 - Beta
Classifier: Intended Audience :: Developers
Classifier: License :: OSI Approved :: MIT License
Classifier: Topic :: Internet :: WWW/HTTP
Classifier: Topic :: Software Development :: Libraries
Classifier: Programming Language :: Python
Classifier: Programming Language :: Python :: 2
Classifier: Programming Language :: Python :: 2.7
Classifier: Programming Language :: Python :: 3
Classifier: Programming Language :: Python :: 3.5
Classifier: Programming Language :: Python :: 3.6
Classifier: Programming Language :: Python :: 3.7
Classifier: Programming Language :: Python :: 3.8
Classifier: Programming Language :: Python :: 3.9
Classifier: Programming Language :: Python :: 3.10
Classifier: Programming Language :: Python :: 3.11
License-File: LICENSE
Requires-Dist: requests
Requires-Dist: msal
Requires-Dist: pytz
Requires-Dist: typing_extensions>=4.0.0
Provides-Extra: ntlmprovider
Requires-Dist: requests_ntlm; extra == "ntlmprovider"
